{
	"hosting": {
		"S3AndCloudFront": {
			"service": "S3AndCloudFront",
			"providerPlugin": "awscloudformation"
		}
	},
	"auth": {
		"agamplify0c96b27c": {
			"service": "Cognito",
			"providerPlugin": "awscloudformation",
			"dependsOn": [],
			"customAuth": false
		}
	},
	"api": {
		"agGQL": {
			"service": "AppSync",
			"providerPlugin": "awscloudformation",
			"output": {
				"authConfig": {
					"additionalAuthenticationProviders": [],
					"defaultAuthentication": {
						"authenticationType": "API_KEY",
						"apiKeyConfig": {
							"description": "createFile",
							"apiKeyExpirationDays": "365"
						}
					}
				}
			}
		}
	}
}